aiourlshortener/__init__.py
aiourlshortener/exceptions.py
aiourlshortener/utils.py
aiourlshortener/shorteners/__init__.py
aiourlshortener/shorteners/base.py
aiourlshortener/shorteners/bitly.py
aiourlshortener/shorteners/google.py
aiourlshortener-0.0.3.dist-info/DESCRIPTION.rst
aiourlshortener-0.0.3.dist-info/METADATA
aiourlshortener-0.0.3.dist-info/RECORD
aiourlshortener-0.0.3.dist-info/WHEEL
aiourlshortener-0.0.3.dist-info/metadata.json
aiourlshortener-0.0.3.dist-info/top_level.txt
