Metadata-Version: 2.0
Name: aiourlshortener
Version: 0.0.3
Summary: asynchronous python3 lib to short long url
Home-page: https://github.com/blikenoother/aiourlshortener
Author: Chirag Patel
Author-email: b.like.no.other@gmail.com
License: MIT
Keywords: asynchronous url shortener
Platform: UNKNOWN
Classifier: Development Status :: 5 - Production/Stable
Classifier: Intended Audience :: Developers
Classifier: Operating System :: OS Independent
Classifier: Programming Language :: Python :: 3
Classifier: Topic :: Internet :: WWW/HTTP :: Dynamic Content
Classifier: Topic :: Software Development :: Libraries :: Python Modules
Requires-Dist: aiohttp
